{
    "editor": "editor",
    "beforeunload": "The board is edited.",
    "completed": "Complete!",
    "cancel": "Cancel",
    "close": "Close",
    "delete": "Delete",
    "menu_file": "File",
    "newboard": "New board",
    "urlinput": "Load from URL",
    "urloutput": "Export URL",
    "fileopen": "Open file",
    "filesave": "Save file as …",
    "duplicate": "Duplicate the board",
    "imagesave": "Save as image file",
    "menu_edit": "Edit",
    "adjust": "Adjust the board",
    "turnflip": "Flip/Turn the board",
    "menu_display": "Display",
    "cellsize": "Cell size",
    "cellsize.xs": "Extra small",
    "cellsize.s": "Small",
    "cellsize.n": "Normal",
    "cellsize.l": "Large",
    "cellsize.xl": "Extra large",
    "cellsize.custom": "Set by number …",
    "font": "Font family",
    "font.sans": "Sans-serif",
    "font.serif": "Serif",
    "dispqnumbg": "Paint background of clue circles",
    "undefcell": "Paint uninputted cells",
    "cursor": "Show cursor",
    "trialmarker": "Show trial markers",
    "adjsize": "Auto size adjust",
    "fullwidth": "Expand canvas width",
    "toolarea.show": "Show tool area",
    "toolarea.hide": "Hide tool area",
    "menu_setting": "Setting",
    "lrinvert": "Invert mouse button",
    "use_tri": "Input type",
    "use_tri.1": "Corner-side",
    "use_tri.2": "Pull-to-input",
    "use_tri.3": "One button",
    "bgcolor.menu": "Input background color",
    "autoerr.menu.hitori": "Show overlapped number",
    "autoerr.menu.gokigen": "Loop slash with color",
    "multierr": "Check multiple errors",
    "forceallcell.menu": "Number in all cells",
    "dirauxmark.menu": "Direction aux. mark",
    "enline.menu": "Line between points",
    "lattice.menu": "Check lattice point",
    "singlenum.menu": "Single number in a region",
    "discolor": "Disable color",
    "autocheck": "Answer check",
    "autocheck.off": "Manual",
    "autocheck.guarded": "Automatic (guarded)",
    "autocheck.simple": "Automatic (always)",
    "menu_help": "Help",
    "rules": "Rules",
    "about": "About pzprxs",
    "translate": "Help us translate",
    "issues": "Bug reports and feature requests",
    "mode": "Mode",
    "mode.edit": "Edit mode",
    "mode.play": "Answer mode",
    "use": "Input Type",
    "use.1": "L/R buttons",
    "use.2": "One button",
    "preset.pentominoes": "Pentominoes",
    "preset.tetrominoes": "Tetrominoes",
    "preset.double_tetrominoes": "Double tetrominoes",
    "preset.copy_answer": "Copy answer to bank",
    "preset.zero": "No pieces",
    "inputmode": "Input Mode",
    "inputmode.auto": "Auto",
    "inputmode.slide": "Slide",
    "inputmode.shade": "Shaded cells",
    "inputmode.unshade": "Unshaded cells",
    "inputmode.number": "Number",
    "inputmode.number-": "Number (rev)",
    "inputmode.letter": "Alphabet",
    "inputmode.letter-": "Alphabet (rev)",
    "inputmode.quesmark": "Question marks",
    "inputmode.quesmark-": "Question marks (rev)",
    "inputmode.color": "Color",
    "inputmode.color-": "Color (rev)",
    "inputmode.border": "Border",
    "inputmode.sub-border": "Sub-border",
    "inputmode.subline": "Aux. conn. lines",
    "inputmode.direc": "Direction",
    "inputmode.arrow": "Arrows",
    "inputmode.circle-unshade": "Unshaded circles",
    "inputmode.circle-shade": "Shaded circles",
    "inputmode.circle-gray": "Gray circles",
    "inputmode.goat": "Goats",
    "inputmode.wolf": "Wolves",
    "inputmode.moon": "Marks of moon",
    "inputmode.sun": "Marks of sun",
    "inputmode.empty": "Invalid cells",
    "inputmode.ice": "Icebarns",
    "inputmode.water": "Water hazard",
    "inputmode.nabe": "Crocks",
    "inputmode.crossdot": "Shaded dots",
    "inputmode.ineq": "Inequality marks",
    "inputmode.move-clue": "Move clue",
    "inputmode.copy-answer": "Copy answer",
    "inputmode.mark-circle": "Circles",
    "inputmode.mark-triangle": "Triangles",
    "inputmode.mark-rect": "Rectangles",
    "inputmode.mark-tree": "Trees",
    "inputmode.mark-tent": "Tents",
    "inputmode.undef": "Question marks",
    "inputmode.line": "Lines",
    "inputmode.peke": "Cross marks",
    "inputmode.diraux": "Aux. dir. marks",
    "inputmode.bar": "Bars",
    "inputmode.akari": "Bulbs",
    "inputmode.star": "Stars",
    "inputmode.dot": "Dots",
    "inputmode.balloon": "Balloons",
    "inputmode.ironball": "Iron balls",
    "inputmode.futon": "Futons",
    "inputmode.completion": "Completion",
    "inputmode.copycircle": "Copy circles",
    "inputmode.copynum": "Copy nums",
    "inputmode.copyletter": "Copy letters",
    "inputmode.dragnum+": "Drag inc. nums",
    "inputmode.dragnum-": "Drag dec. nums",
    "inputmode.objblank": "Aux. dots",
    "inputmode.numexist": "Aux. circles",
    "inputmode.numblank": "Aux. crosses",
    "inputmode.subcircle": "Aux. circles",
    "inputmode.subcross": "Aux. crosses",
    "inputmode.bgcolor": "Bgcolor 1/2",
    "inputmode.bgcolor1": "Bgcolor 1",
    "inputmode.bgcolor2": "Bgcolor 2",
    "inputmode.bgpaint": "Draft sketch",
    "inputmode.clear": "Erase data",
    "inputmode.info-line": "Check line connection",
    "inputmode.info-blk": "Check shaded cell connection",
    "inputmode.info-road": "Check route",
    "disptype": "Display",
    "disptype_yajilin.1": "Original style",
    "disptype_yajilin.2": "Gray background",
    "disptype_bosanowa.1": "Original style",
    "disptype_bosanowa.2": "Sokoban style",
    "disptype_bosanowa.3": "Waritai style",
    "disptype_interbd.1": "Colors",
    "disptype_interbd.2": "Shapes",
    "disptype_interbd.3": "Both",
    "dispmove": "Display as object moving",
    "bgcolor.tool": "Allow inputting background color when cell center is clicked",
    "autocmp.number": "Grey each correct number",
    "autocmp.room": "Paint background of each completed block",
    "autocmp.akari": "Paint background of each illuminated block",
    "autocmp.kouchoku": "Grey each letter which links over two segments",
    "autocmp.border": "Grey border between different areas",
    "autoerr.tool.hitori": "Show overlapped number as red",
    "autoerr.tool.gokigen": "Draw loop line as red",
    "autoerr.tool.wagiri": "Draw loop line as bold",
    "dirauxmark.tool": "Enable to input aux mark of direction",
    "enline.tool": "Enable to draw line only between the points",
    "lattice.tool": "Disable drawing segment passing over a lattice point",
    "uramashu": "Change to Ura-Mashu",
    "singlenum.tool": "Ensure that a region has a number",
    "singleregion": "Ensure that only one tile is shaded in each region",
    "forceallcell.tool": "Force each cell to have a number",
    "snakebd": "Draw border around a snake",
    "ensquare": "Enable to force drawing squares from a clue",
    "keypopup.tool": "Input numbers by panel",
    "irowake.tool": "Color each line",
    "irowake.change": "Change the line colors",
    "irowakeblk.tool": "Color each block",
    "irowakeblk.change": "Change the block colors",
    "dontpassallcell": "Lines need not pass all crossings",
    "aquarium_regions": "Water in one region must have the same surface level",
    "country_empty": "Areas don't have to be visited",
    "voxas_tatami": "Tatami rules (no 4-way intersections)",
    "tren_new": "All unused cells must be connected",
    "nuriuzu_connect": "All shaded cells must be connected",
    "variant": "This puzzle uses variant rules",
    "time": "Time:",
    "check": "Check",
    "check.variant": "Check base type",
    "undo": "<-",
    "redo": "->",
    "ansclear": "Erase answer",
    "ansclear.confirm": "Do you want to erase the answer?",
    "subclear": "Erase aux. marks",
    "subclear.confirm": "Do you want to erase the auxiliary marks?",
    "auxdelete.confirm": "Do you want to delete this piece?",
    "encolorall": "Color up",
    "flushexcell": "Flush clues",
    "applypreset": "Replace bank",
    "applypreset.title": "Replace bank",
    "applypreset.submit": "Replace",
    "dropblocks": "Drop blocks",
    "enterTrial": "Trial mode",
    "acceptTrial": "Accept trial",
    "rejectTrial": "Reject trial",
    "enterFurtherTrial": "Enter further trial",
    "newboard.title": "New Board",
    "newboard.header": "Create New Board.",
    "newboard.cols": "Cols",
    "newboard.tawa.width": "Width (Yellows)",
    "newboard.rows": "Rows",
    "newboard.tawa.height": "Height",
    "newboard.preset": "Preset",
    "newboard.submit": "Create",
    "urlinput.title": "Load from URL",
    "urlinput.submit": "Load",
    "urloutput.title": "Export URL",
    "urloutput.kanpen": "Change to Kanpen URL",
    "urloutput.heyaapp": "Change to Heyawake-Applet URL",
    "urloutput.pzprv3e": "Change to PUZ-PRE v3 Re-Edit URL",
    "fileopen.title": "Open File",
    "fileopen.choose": "Choose file",
    "filesave.title": "Save File",
    "filesave.format": "File format",
    "filesave.format.pzprv3": "Puz-Pre v3 format",
    "filesave.format.penciltxt": "Pencilbox Text format",
    "filesave.format.pencilxml": "Pencilbox XML format",
    "filesave.filename": "Filename",
    "filesave.submit": "Save",
    "filesave.invalid": "The filename contains invalid characters.",
    "imagesave.title": "Save Image",
    "imagesave.filetype": "File format",
    "imagesave.png": "PNG Format",
    "imagesave.svg": "Vector Image (SVG)",
    "imagesave.gif": "GIF Format",
    "imagesave.jpeg": "jpeg Format",
    "imagesave.webp": "webp Format",
    "imagesave.filename": "Filename",
    "imagesave.cellsize": "Image Size",
    "imagesave.transparent": "Set background to transparent",
    "imagesave.saveimage": "Download",
    "imagesave.openimage": "Open in another window",
    "imagesave.error": "Fail to Output the Image",
    "adjust.title": "Board Dimension Resizer",
    "adjust.header": "Adjust the board.",
    "adjust.expand": "Expand",
    "adjust.reduce": "Reduce",
    "adjust.up": "Top",
    "adjust.dn": "Bottom",
    "adjust.lt": "Left",
    "adjust.rt": "Right",
    "turnflip.title": "Flip/Turn the board",
    "turnflip.header": "Flip/Turn the board.",
    "turnflip.turnl": "Turn left by 90 degree",
    "turnflip.turnr": "Turn right by 90 degree",
    "turnflip.flipy": "Flip upside down",
    "turnflip.flipx": "Flip leftside right",
    "turnflip.turnl.short": "↶",
    "turnflip.turnr.short": "↷",
    "turnflip.flipy.short": "⇅",
    "turnflip.flipx.short": "⇄",
    "dispsize.title": "Change size",
    "dispsize.header": "Change the display size.",
    "dispsize.cellsize": "Display size",
    "dispsize.submit": "Change",
    "about.title": "About pzprxs",
    "about.pzv": "PUZ-PRE v3",
    "about.author": "happa",
    "network.title": "Network play"
}
